dir2pdf.py
dir2pdf-0.0.3.dist-info/LICENSE
dir2pdf-0.0.3.dist-info/METADATA
dir2pdf-0.0.3.dist-info/WHEEL
dir2pdf-0.0.3.dist-info/entry_points.txt
dir2pdf-0.0.3.dist-info/top_level.txt
dir2pdf-0.0.3.dist-info/RECORD
