Metadata-Version: 2.1
Name: dir2pdf
Version: 0.0.3
Summary: Convert directories of images to PDFs
Home-page: https://github.com/jirassimok/dir2pdf
Author: Jacob Komissar
License: UNKNOWN
Platform: UNKNOWN
Classifier: Environment :: Console
Classifier: License :: OSI Approved :: MIT License
Classifier: Operating System :: OS Independent
Requires-Python: >=3.7
Requires-Dist: Pillow
Provides-Extra: dev
Requires-Dist: flake8 ; extra == 'dev'
